leicascanningtemplate/__init__.py
leicascanningtemplate/template.py
leicascanningtemplate/VERSION
leicascanningtemplate-0.0.3.dist-info/DESCRIPTION.rst
leicascanningtemplate-0.0.3.dist-info/METADATA
leicascanningtemplate-0.0.3.dist-info/metadata.json
leicascanningtemplate-0.0.3.dist-info/RECORD
leicascanningtemplate-0.0.3.dist-info/top_level.txt
leicascanningtemplate-0.0.3.dist-info/WHEEL
