Metadata-Version: 2.0
Name: leicascanningtemplate
Version: 0.0.3
Summary: convenience library for talking with leica matrix screener scanning templates
Home-page: https://github.com/arve0/leicascanningtemplate
Author: Arve Seljebu
Author-email: arve.seljebu@gmail.com
License: MIT
Keywords: leicascanningtemplate
Platform: UNKNOWN
Classifier: Development Status :: 3 - Alpha
Classifier: Intended Audience :: Developers
Classifier: License :: OSI Approved :: MIT License
Classifier: Natural Language :: English
Classifier: Programming Language :: Python :: 2
Classifier: Programming Language :: Python :: 2.7
Classifier: Programming Language :: Python :: 3
Classifier: Programming Language :: Python :: 3.4
Requires-Dist: lxml
